aws_pdk/__init__.py
aws_pdk/py.typed
aws_pdk/_jsii/__init__.py
aws_pdk/_jsii/pdk@0.26.14.jsii.tgz
aws_pdk/aws_arch/__init__.py
aws_pdk/aws_arch/aws_arch/__init__.py
aws_pdk/aws_arch/aws_arch/drawio_spec/__init__.py
aws_pdk/aws_arch/aws_arch/drawio_spec/aws4/__init__.py
aws_pdk/aws_arch/aws_arch/pricing_manifest/__init__.py
aws_pdk/cdk_graph/__init__.py
aws_pdk/cdk_graph_plugin_diagram/__init__.py
aws_pdk/cdk_graph_plugin_threat_composer/__init__.py
aws_pdk/cloudscape_react_ts_website/__init__.py
aws_pdk/identity/__init__.py
aws_pdk/infrastructure/__init__.py
aws_pdk/monorepo/__init__.py
aws_pdk/monorepo/nx/__init__.py
aws_pdk/monorepo/syncpack/__init__.py
aws_pdk/monorepo/syncpack/base_group_config/__init__.py
aws_pdk/monorepo/syncpack/custom_type_config/__init__.py
aws_pdk/monorepo/syncpack/semver_group_config/__init__.py
aws_pdk/monorepo/syncpack/version_group_config/__init__.py
aws_pdk/pdk_nag/__init__.py
aws_pdk/pipeline/__init__.py
aws_pdk/static_website/__init__.py
aws_pdk/type_safe_api/__init__.py
aws_pdk-0.26.14.data/scripts/monorepo.nx-dir-hasher
aws_pdk-0.26.14.data/scripts/pdk
aws_pdk-0.26.14.data/scripts/type-safe-api
aws_pdk-0.26.14.dist-info/LICENSE
aws_pdk-0.26.14.dist-info/METADATA
aws_pdk-0.26.14.dist-info/WHEEL
aws_pdk-0.26.14.dist-info/top_level.txt
aws_pdk-0.26.14.dist-info/RECORD
