Metadata-Version: 2.1
Name: aws_pdk
Version: 0.26.14
Summary: @aws/pdk
Home-page: https://github.com/aws/aws-pdk
Author: AWS APJ COPE<apj-cope@amazon.com>
License: Apache-2.0
Project-URL: Source, https://github.com/aws/aws-pdk
Classifier: Intended Audience :: Developers
Classifier: Operating System :: OS Independent
Classifier: Programming Language :: JavaScript
Classifier: Programming Language :: Python :: 3 :: Only
Classifier: Programming Language :: Python :: 3.8
Classifier: Programming Language :: Python :: 3.9
Classifier: Programming Language :: Python :: 3.10
Classifier: Programming Language :: Python :: 3.11
Classifier: Typing :: Typed
Classifier: Development Status :: 5 - Production/Stable
Classifier: License :: OSI Approved
Requires-Python: ~=3.8
License-File: LICENSE
Requires-Dist: aws-cdk-lib<3.0.0,>=2.163.1
Requires-Dist: aws-cdk.aws-cognito-identitypool-alpha<3.0.0,>=2.163.1.a0
Requires-Dist: cdk-nag<3.0.0,>=2.31.0
Requires-Dist: constructs<11.0.0,>=10.4.2
Requires-Dist: jsii<2.0.0,>=1.104.0
Requires-Dist: projen<0.83.0,>=0.82.8
Requires-Dist: publication>=0.0.3
Requires-Dist: typeguard<4.3.0,>=2.13.3
